front11_cmd/__init__.py
front11_cmd/front11_cmd.py
Front11_cmd-0.3.4.dist-info/METADATA
Front11_cmd-0.3.4.dist-info/WHEEL
Front11_cmd-0.3.4.dist-info/entry_points.txt
Front11_cmd-0.3.4.dist-info/top_level.txt
Front11_cmd-0.3.4.dist-info/RECORD
