Metadata-Version: 2.1
Name: Front11_cmd
Version: 0.3.4
Summary: Default template for PDM package
Author-email: Nicou11 <lyoungin1204@gmail.com>
License: MIT
Project-URL: Homepage, https://github.com/nicou11/Front11_cmd
Requires-Python: >=3.9
Requires-Dist: Front11-div >=0.3.0
Requires-Dist: Front11-multi >=0.1.2
Requires-Dist: Front11-plus >=0.1.3
